odinmcp/__init__.py
odinmcp/cli/__init__.py
odinmcp/cli/main.py
odinmcp/config.py
odinmcp/constants.py
odinmcp/main.py
odinmcp/models/__init__.py
odinmcp/models/auth.py
odinmcp/web/__init__.py
odinmcp/web/main.py
odinmcp/web/middleware/__init__.py
odinmcp/web/middleware/heimdall.py
odinmcp/web/middleware/hermod.py
odinmcp/web/transports/__init__.py
odinmcp/web/transports/http_streaming.py
odinmcp/worker/__init__.py
odinmcp/worker/main.py
odinmcp/worker/session.py
odinmcp-0.1.0.dist-info/LICENSE
odinmcp-0.1.0.dist-info/METADATA
odinmcp-0.1.0.dist-info/WHEEL
odinmcp-0.1.0.dist-info/entry_points.txt
odinmcp-0.1.0.dist-info/RECORD
