Metadata-Version: 2.3
Name: odinmcp
Version: 0.1.0
Summary: 
Keywords: mcp,mcp server,mcp worker,model context protocol,odinmcp,llm,agent
Author: theNullP0inter
Author-email: nikhilallamsetti@gmail.com
Requires-Python: >=3.11
Classifier: Programming Language :: Python :: 3
Classifier: Programming Language :: Python :: 3.11
Classifier: Programming Language :: Python :: 3.12
Classifier: Programming Language :: Python :: 3.13
Requires-Dist: asgiref (>=3.8.1,<4.0.0)
Requires-Dist: celery[redis] (>=5.5.2,<6.0.0)
Requires-Dist: mcp (>=1.9.2,<2.0.0)
Requires-Dist: pyjwt (>=2.10.1,<3.0.0)
Requires-Dist: requests (>=2.32.3,<3.0.0)
Requires-Dist: starlette (>=0.47.0,<0.48.0)
Requires-Dist: typer (>=0.16.0,<0.17.0)
Requires-Dist: uvicorn (>=0.34.2,<0.35.0)
Requires-Dist: zmq (>=0.0.0,<0.0.1)
